pickle_wrap/__init__.py
pickle_wrap/pickle_wrap.py
pickle_wrap-3.0.1.dist-info/LICENSE
pickle_wrap-3.0.1.dist-info/METADATA
pickle_wrap-3.0.1.dist-info/WHEEL
pickle_wrap-3.0.1.dist-info/top_level.txt
pickle_wrap-3.0.1.dist-info/RECORD
