Metadata-Version: 2.1
Name: pickle-wrap
Version: 3.0.1
Summary: Wraps pickles
Home-page: https://github.com/paulcbogdan/pickle_wrap
Author: paulcbogdan
Author-email: paulcbogdan@gmail.com
License: MIT
Keywords: pickling,wrapping
Platform: UNKNOWN
Requires-Python: >=3
License-File: LICENSE
